code_intelligence-4.10.0.dist-info/METADATA
code_intelligence-4.10.0.dist-info/RECORD
code_intelligence-4.10.0.dist-info/WHEEL
code_intelligence/__init__.py
code_intelligence/goober.py
code_intelligence/libcode_intelligence.so
code_intelligence/py.typed