Metadata-Version: 2.1
Name: code_intelligence
Version: 4.10.0
Summary: Code intelligence library
